hyc/__init__.py
hyc/fraction.py
hyc/num.py
hyc-3.3.0.dist-info/LICENSE
hyc-3.3.0.dist-info/METADATA
hyc-3.3.0.dist-info/WHEEL
hyc-3.3.0.dist-info/top_level.txt
hyc-3.3.0.dist-info/RECORD
